{"file":"num2.png","frames":{
"0":{"x":62,"y":34,"w":23,"h":30,"offX":0,"offY":0,"sourceW":23,"sourceH":30},
"1":{"x":1,"y":67,"w":16,"h":29,"offX":0,"offY":0,"sourceW":16,"sourceH":29},
"2":{"x":1,"y":35,"w":22,"h":30,"offX":0,"offY":0,"sourceW":22,"sourceH":30},
"3":{"x":62,"y":1,"w":23,"h":31,"offX":0,"offY":0,"sourceW":23,"sourceH":31},
"4":{"x":87,"y":1,"w":24,"h":29,"offX":0,"offY":0,"sourceW":24,"sourceH":29},
"5":{"x":87,"y":64,"w":23,"h":29,"offX":0,"offY":0,"sourceW":23,"sourceH":29},
"6":{"x":37,"y":1,"w":23,"h":31,"offX":0,"offY":0,"sourceW":23,"sourceH":31},
"7":{"x":25,"y":66,"w":22,"h":29,"offX":0,"offY":0,"sourceW":22,"sourceH":29},
"8":{"x":87,"y":32,"w":23,"h":30,"offX":0,"offY":0,"sourceW":23,"sourceH":30},
"9":{"x":37,"y":34,"w":23,"h":30,"offX":0,"offY":0,"sourceW":23,"sourceH":30},
"dot":{"x":25,"y":35,"w":7,"h":7,"offX":1,"offY":22,"sourceW":9,"sourceH":29},
"per":{"x":1,"y":1,"w":34,"h":32,"offX":0,"offY":0,"sourceW":34,"sourceH":32}}}