{
	"groups":[
	{
		"keys":"31,41,111_fnt,111_png,555,animate1_json,animate1_png,bg,bomb_json,bomb_png,crash_json,crash_png,gray_font_fnt,gray_font_png,highCombo,infoBg,infoBtn,moreBtn,new,orange_font_fnt,orange_font_png,overBg,readygo_json,readygo_png,red_font_fnt,red_font_png,restartBtn,sbt,shareBtn,soundBtn1,soundBtn2,warning_json,warning_png,yellow_font_fnt,yellow_font_png,11,21,newer_des2,newer_des3,newer_des4,newer_des5,newerHandMc_json,newerHandMc_png,newer_des1",
		"name":"preload2"
	},
	{
		"keys":"3",
		"name":"loading"
	},
	{
		"keys":"bomb,add,great,good,bonus,readygo,warning,ui_click,amazing",
		"name":"sound1"
	},
	{
		"keys":"music",
		"name":"sound2"
	}],
	"resources":[
	{
		"name":"music",
		"soundType":"music",
		"type":"sound",
		"url":"assets/music2.mp3"
	},
	{
		"name":"bomb",
		"soundType":"effect",
		"type":"sound",
		"url":"assets/bomb.mp3"
	},
	{
		"name":"add",
		"soundType":"effect",
		"type":"sound",
		"url":"assets/add.mp3"
	},
	{
		"name":"readygo",
		"soundType":"effect",
		"type":"sound",
		"url":"assets/readygo.mp3"
	},
	{
		"name":"ui_click",
		"soundType":"effect",
		"type":"sound",
		"url":"assets/ui_click.mp3"
	},
	{
		"name":"warning",
		"soundType":"effect",
		"type":"sound",
		"url":"assets/warning.mp3"
	},
	{
		"name":"amazing",
		"soundType":"effect",
		"type":"sound",
		"url":"assets/amazing.mp3"
	},
	{
		"name":"bonus",
		"soundType":"effect",
		"type":"sound",
		"url":"assets/bonus.mp3"
	},
	{
		"name":"good",
		"soundType":"effect",
		"type":"sound",
		"url":"assets/good.mp3"
	},
	{
		"name":"great",
		"soundType":"effect",
		"type":"sound",
		"url":"assets/great.mp3"
	},
	{
		"name":"31",
		"type":"image",
		"url":"assets/small/31.png"
	},
	{
		"name":"41",
		"type":"image",
		"url":"assets/small/41.png"
	},
	{
		"name":"111_fnt",
		"type":"font",
		"url":"assets/small/111.fnt"
	},
	{
		"name":"111_png",
		"type":"image",
		"url":"assets/small/111.png"
	},
	{
		"name":"555",
		"type":"image",
		"url":"assets/small/555.png"
	},
	{
		"name":"animate1_json",
		"type":"json",
		"url":"assets/small/animate1.json"
	},
	{
		"name":"animate1_png",
		"type":"image",
		"url":"assets/small/animate1.png"
	},
	{
		"name":"bg",
		"type":"image",
		"url":"assets/small/bg.jpg"
	},
	{
		"name":"bomb_json",
		"type":"json",
		"url":"assets/small/bomb.json"
	},
	{
		"name":"bomb_png",
		"type":"image",
		"url":"assets/small/bomb.png"
	},
	{
		"name":"crash_json",
		"type":"json",
		"url":"assets/small/crash.json"
	},
	{
		"name":"crash_png",
		"type":"image",
		"url":"assets/small/crash.png"
	},
	{
		"name":"gray_font_fnt",
		"type":"font",
		"url":"assets/small/gray_font.fnt"
	},
	{
		"name":"gray_font_png",
		"type":"image",
		"url":"assets/small/gray_font.png"
	},
	{
		"name":"highCombo",
		"type":"image",
		"url":"assets/small/highCombo.png"
	},
	{
		"name":"infoBg",
		"type":"image",
		"url":"assets/small/infoBg.png"
	},
	{
		"name":"infoBtn",
		"type":"image",
		"url":"assets/small/infoBtn.png"
	},
	{
		"name":"moreBtn",
		"type":"image",
		"url":"assets/small/moreBtn.png"
	},
	{
		"name":"new",
		"type":"image",
		"url":"assets/small/new.png"
	},
	{
		"name":"orange_font_fnt",
		"type":"font",
		"url":"assets/small/orange_font.fnt"
	},
	{
		"name":"orange_font_png",
		"type":"image",
		"url":"assets/small/orange_font.png"
	},
	{
		"name":"overBg",
		"type":"image",
		"url":"assets/small/overBg.png"
	},
	{
		"name":"readygo_json",
		"type":"json",
		"url":"assets/small/readygo.json"
	},
	{
		"name":"readygo_png",
		"type":"image",
		"url":"assets/small/readygo.png"
	},
	{
		"name":"red_font_fnt",
		"type":"font",
		"url":"assets/small/red_font.fnt"
	},
	{
		"name":"red_font_png",
		"type":"image",
		"url":"assets/small/red_font.png"
	},
	{
		"name":"restartBtn",
		"type":"image",
		"url":"assets/small/restartBtn.png"
	},
	{
		"name":"sbt",
		"type":"image",
		"url":"assets/small/sbt.png"
	},
	{
		"name":"shareBtn",
		"type":"image",
		"url":"assets/small/shareBtn.png"
	},
	{
		"name":"soundBtn1",
		"type":"image",
		"url":"assets/small/soundBtn1.png"
	},
	{
		"name":"soundBtn2",
		"type":"image",
		"url":"assets/small/soundBtn2.png"
	},
	{
		"name":"warning_json",
		"type":"json",
		"url":"assets/small/warning.json"
	},
	{
		"name":"warning_png",
		"type":"image",
		"url":"assets/small/warning.png"
	},
	{
		"name":"yellow_font_fnt",
		"type":"font",
		"url":"assets/small/yellow_font.fnt"
	},
	{
		"name":"yellow_font_png",
		"type":"image",
		"url":"assets/small/yellow_font.png"
	},
	{
		"name":"11",
		"type":"image",
		"url":"assets/small/11.png"
	},
	{
		"name":"21",
		"type":"image",
		"url":"assets/small/21.png"
	},
	{
		"name":"3",
		"type":"image",
		"url":"assets/small/3.png"
	},
	{
		"name":"newerHandMc_json",
		"type":"json",
		"url":"assets/small/newer/newerHandMc.json"
	},
	{
		"name":"newerHandMc_png",
		"type":"image",
		"url":"assets/small/newer/newerHandMc.png"
	},
	{
		"name":"newer_des1",
		"type":"image",
		"url":"assets/small/newer/newer_des1.png"
	},
	{
		"name":"newer_des2",
		"type":"image",
		"url":"assets/small/newer/newer_des2.png"
	},
	{
		"name":"newer_des3",
		"type":"image",
		"url":"assets/small/newer/newer_des3.png"
	},
	{
		"name":"newer_des4",
		"type":"image",
		"url":"assets/small/newer/newer_des4.png"
	},
	{
		"name":"newer_des5",
		"type":"image",
		"url":"assets/small/newer/newer_des5.png"
	}]
}