{ "height":61,
 "layers":[
        {
         "draworder":"topdown",
         "height":0,
         "name":"objects",
         "objects":[
                {
                 "height":60,
                 "name":"w1",
                 "properties":
                    {

                    },
                 "rotation":0,
                 "type":"wood",
                 "visible":true,
                 "width":70,
                 "x":170,
                 "y":370
                }, 
                {
                 "height":50,
                 "name":"g1",
                 "properties":
                    {

                    },
                 "rotation":0,
                 "type":"good",
                 "visible":true,
                 "width":50,
                 "x":180,
                 "y":320
                }, 
                {
                 "height":40,
                 "name":"",
                 "properties":
                    {
                     "object":"o1"
                    },
                 "rotation":0,
                 "type":"pivot_joint",
                 "visible":true,
                 "width":20,
                 "x":240,
                 "y":210
                }, 
                {
                 "height":60,
                 "name":"w1",
                 "properties":
                    {

                    },
                 "rotation":0,
                 "type":"wood",
                 "visible":true,
                 "width":70,
                 "x":170,
                 "y":430
                }, 
                {
                 "height":60,
                 "name":"w1",
                 "properties":
                    {

                    },
                 "rotation":0,
                 "type":"wood",
                 "visible":true,
                 "width":70,
                 "x":170,
                 "y":490
                }, 
                {
                 "height":60,
                 "name":"w1",
                 "properties":
                    {

                    },
                 "rotation":0,
                 "type":"wood",
                 "visible":true,
                 "width":70,
                 "x":170,
                 "y":550
                }, 
                {
                 "height":60,
                 "name":"og2",
                 "properties":
                    {

                    },
                 "rotation":0,
                 "type":"goal",
                 "visible":true,
                 "width":60,
                 "x":10,
                 "y":440
                }, 
                {
                 "height":60,
                 "name":"o1",
                 "properties":
                    {

                    },
                 "rotation":0,
                 "type":"stone",
                 "visible":true,
                 "width":250,
                 "x":230,
                 "y":180
                }, 
                {
                 "height":20,
                 "name":"s1",
                 "properties":
                    {
                     "static":"true"
                    },
                 "rotation":0,
                 "type":"stone",
                 "visible":true,
                 "width":80,
                 "x":0,
                 "y":500
                }, 
                {
                 "height":60,
                 "name":"w2",
                 "properties":
                    {
                     "static":"true"
                    },
                 "rotation":0,
                 "type":"wood",
                 "visible":true,
                 "width":70,
                 "x":410,
                 "y":240
                }],
         "opacity":1,
         "type":"objectgroup",
         "visible":true,
         "width":0,
         "x":0,
         "y":0
        }],
 "orientation":"orthogonal",
 "properties":
    {
     "star_1":"5",
     "star_2":"4",
     "star_3":"3"
    },
 "renderorder":"right-down",
 "tileheight":10,
 "tilesets":[],
 "tilewidth":10,
 "version":1,
 "width":48
}